mintigomarketorest/__init__.py
mintigomarketorest/client.py
mintigomarketorest/helper/__init__.py
mintigomarketorest/helper/exceptions.py
mintigomarketorest/helper/http_lib.py
mintigomarketorest-0.0.5.dist-info/DESCRIPTION.rst
mintigomarketorest-0.0.5.dist-info/METADATA
mintigomarketorest-0.0.5.dist-info/RECORD
mintigomarketorest-0.0.5.dist-info/WHEEL
mintigomarketorest-0.0.5.dist-info/metadata.json
mintigomarketorest-0.0.5.dist-info/top_level.txt
