Metadata-Version: 2.0
Name: mintigomarketorest
Version: 0.0.5
Summary: Python Client for Mintigo for the Marketo REST API
Home-page: https://bitbucket.org/mintigo/marketo-rest-python
Author: Eliram Shatz
Author-email: eliram@mintigo.com
License: MIT License
Keywords: Marketo,Mintigo,REST API,Wrapper,Client
Platform: UNKNOWN
Requires-Dist: requests (==2.10.0)
